README.md
setup.py
exif2timestream_scripts/__init__.py
exif2timestream_scripts/exif2timestream_batch.py
exif2timestream_scripts/exif2timestream_cli.py
exif2timestream_v2.egg-info/PKG-INFO
exif2timestream_v2.egg-info/SOURCES.txt
exif2timestream_v2.egg-info/dependency_links.txt
exif2timestream_v2.egg-info/entry_points.txt
exif2timestream_v2.egg-info/requires.txt
exif2timestream_v2.egg-info/top_level.txt
libexif2timestream2/__init__.py
libexif2timestream2/archiver.py
libexif2timestream2/directorydb.py
libexif2timestream2/exif.py
libexif2timestream2/image.py
libexif2timestream2/process.py
libexif2timestream2/time.py