Metadata-Version: 1.1
Name: exif2timestream-v2
Version: 0.10.7
Summary: A tool to turn unstructured timelapses into nested directory trees with downsampled images based on exif data.
Home-page: https://borevitzlab.github.io/exif2timestream/
Author: Gareth Dunstone, Borevitz Lab, Australian Plant Phenomics Facility, TimeScience
Author-email: appf@anu.edu.au
License: GPLv3
Keywords: timelapse,imaging
Platform: UNKNOWN
Classifier: Development Status :: 4 - Beta
Classifier: Environment :: Console
Classifier: Intended Audience :: Science/Research
Classifier: Operating System :: Unix
Classifier: Programming Language :: Python :: 3 :: Only
